{
  "type": "FeatureCollection",
  "features": [
    {
      "type": "Feature",
      "properties": {
        "title": "One"
      },
      "geometry": {
        "type": "Point",
        "coordinates": [
          -82.10116267204285,
          39.32739287379205
        ]
      }
    },
    {
      "type": "Feature",
      "properties": {
        "title": "Two"
      },
      "geometry": {
        "type": "Point",
        "coordinates": [
          -79.89073544740677,
          40.43336571835535
        ]
      }
    }
  ]
}